Metadata-Version: 1.0
Name: dist-probability-ns
Version: 0.1
Summary: Gaussian dist_probability_ns
Home-page: UNKNOWN
Author: Nicolas Schuldt
Author-email: schuldtnicolass@gmail.com
License: UNKNOWN
Platform: UNKNOWN
